Workbook

Sheet How-To
A1: How to use this Inventory Tracker
A2: Yellow cells are for you to type in. White cells are formulas, so don't type over them.
A4: 1. PRODUCTS: add one row per SKU: SKU, name, category, unit cost, selling price, opening stock and reorder level.
A5: Received, Incoming, Sold, Current Stock, Stock Value, Status and Days of Stock Left calculate automatically.
A6: Rows turn YELLOW when stock is at or below the reorder level, and RED when stock is 0 or below.
A7: 2. STOCK IN: log every purchase order or delivery. Pick the SKU from the dropdown.
A8: Status = 'Incoming' while it's on the way (counted as Incoming); change it to 'Received' when it arrives (added to stock).
A9: 3. SALES: log sales (or paste a daily export from Amazon / Shopify): Date, SKU, Quantity, Channel, Order ID.
A10: Unit price and revenue are looked up from Products automatically. 'SKU not found' means a typo or a missing product.
A11: 4. DASHBOARD: totals, items to reorder, out-of-stock count, revenue by channel and a stock chart. Nothing to edit.
A13: Status meanings
A14: OK = above reorder level | REORDER NOW = at/below reorder level, nothing on order | LOW - ON ORDER = low but a PO is incoming | OUT OF STOCK = 0 or less
... A22: Assumptions (dataset has no stock or cost data): opening stock on 1 Nov 2011 = 60 days of avg daily demand (Dec 2010-Oct 2011); reorder level = 14 days; unit cost = 60% of avg selling price; stock cannot go below 0.

Sheet Products
A1: SKU | B1: Product Name | C1: Category | D1: Unit Cost | E1: Selling Price | F1: Opening Stock | G1: Reorder Level | H1: Received | I1: Incoming (on order) | J1: Sold | K1: Current Stock | L1: Stock Value | M1: Status | N1: Units Sold (30d) | O1: Days of Stock Left
A2: 85123A | B2: White Hanging Heart T-Light Holder | C2: Lighting | D2: 1.67 | E2: 2.78 | F2: 5720 | G2: 1335 | H2: =IF($A2="","",SUMIFS('Stock In'!$C:$C,'Stock In'!$B:$B,$A2,'Stock In'!$E:$E,"Received")) | I2: =IF($A2="","",SUMIFS('Stock In'!$C:$C,'Stock In'!$B:$B,$A2,'Stock In'!$E:$E,"Incoming")) | J2: =IF($A2="","",SUMIFS(Sales!$C:$C,Sales!$B:$B,$A2)) | K2: =IF($A2="","",MAX(0,N($F2)+N($H2)-N($J2))) | L2: =IF($A2="","",$K2*N($D2)) | M2: =IF($A2="","",IF($K2<=0,"OUT OF STOCK",IF($K2<=N($G2),IF(N($I2)>0,"LOW - ON ORDER","REORDER NOW"),"OK"))) | N2: =IF($A2="","",SUMIFS(Sales!$C:$C,Sales!$B:$B,$A2,Sales!$A:$A,">="&(TODAY()-30))) | O2: =IF($A2="","",IF(N($N2)=0,"no recent sales",MAX(0,ROUND($K2/($N2/30),0))))
A3: 85099B | B3: Jumbo Bag Red Retrospot | C3: Bags | D3: 1.17 | E3: 1.95 | F3: 7426 | G3: 1733 | H3: =IF($A3="","",SUMIFS('Stock In'!$C:$C,'Stock In'!$B:$B,$A3,'Stock In'!$E:$E,"Received")) | I3: =IF($A3="","",SUMIFS('Stock In'!$C:$C,'Stock In'!$B:$B,$A3,'Stock In'!$E:$E,"Incoming")) | J3: =IF($A3="","",SUMIFS(Sales!$C:$C,Sales!$B:$B,$A3)) | K3: =IF($A3="","",MAX(0,N($F3)+N($H3)-N($J3))) | L3: =IF($A3="","",$K3*N($D3)) | M3: =IF($A3="","",IF($K3<=0,"OUT OF STOCK",IF($K3<=N($G3),IF(N($I3)>0,"LOW - ON ORDER","REORDER NOW"),"OK"))) | N3: =IF($A3="","",SUMIFS(Sales!$C:$C,Sales!$B:$B,$A3,Sales!$A:$A,">="&(TODAY()-30))) | O3: =IF($A3="","",IF(N($N3)=0,"no recent sales",MAX(0,ROUND($K3/($N3/30),0))))
A4: 22423 | B4: Regency Cakestand 3 Tier | C4: Kitchen | D4: 7.54 | E4: 12.57 | F4: 2216 | G4: 517 | H4: =IF($A4="","",SUMIFS('Stock In'!$C:$C,'Stock In'!$B:$B,$A4,'Stock In'!$E:$E,"Received")) | I4: =IF($A4="","",SUMIFS('Stock In'!$C:$C,'Stock In'!$B:$B,$A4,'Stock In'!$E:$E,"Incoming")) | J4: =IF($A4="","",SUMIFS(Sales!$C:$C,Sales!$B:$B,$A4)) | K4: =IF($A4="","",MAX(0,N($F4)+N($H4)-N($J4))) | L4: =IF($A4="","",$K4*N($D4)) | M4: =IF($A4="","",IF($K4<=0,"OUT OF STOCK",IF($K4<=N($G4),IF(N($I4)>0,"LOW - ON ORDER","REORDER NOW"),"OK"))) | N4: =IF($A4="","",SUMIFS(Sales!$C:$C,Sales!$B:$B,$A4,Sales!$A:$A,">="&(TODAY()-30))) | O4: =IF($A4="","",IF(N($N4)=0,"no recent sales",MAX(0,ROUND($K4/($N4/30),0))))
A5: 47566 | B5: Party Bunting | C5: Kitchen | D5: 3.26 | E5: 5.44 | F5: 3088 | G5: 721 | H5: =IF($A5="","",SUMIFS('Stock In'!$C:$C,'Stock In'!$B:$B,$A5,'Stock In'!$E:$E,"Received")) | I5: =IF($A5="","",SUMIFS('Stock In'!$C:$C,'Stock In'!$B:$B,$A5,'Stock In'!$E:$E,"Incoming")) | J5: =IF($A5="","",SUMIFS(Sales!$C:$C,Sales!$B:$B,$A5)) | K5: =IF($A5="","",MAX(0,N($F5)+N($H5)-N($J5))) | L5: =IF($A5="","",$K5*N($D5)) | M5: =IF($A5="","",IF($K5<=0,"OUT OF STOCK",IF($K5<=N($G5),IF(N($I5)>0,"LOW - ON ORDER","REORDER NOW"),"OK"))) | N5: =IF($A5="","",SUMIFS(Sales!$C:$C,Sales!$B:$B,$A5,Sales!$A:$A,">="&(TODAY()-30))) | O5: =IF($A5="","",IF(N($N5)=0,"no recent sales",MAX(0,ROUND($K5/($N5/30),0))))
A6: 20725 | B6: Lunch Bag Red Retrospot | C6: Bags | D6: 1.11 | E6: 1.84 | F6: 3074 | G6: 717 | H6: =IF($A6="","",SUMIFS('Stock In'!$C:$C,'Stock In'!$B:$B,$A6,'Stock In'!$E:$E,"Received")) | I6: =IF($A6="","",SUMIFS('Stock In'!$C:$C,'Stock In'!$B:$B,$A6,'Stock In'!$E:$E,"Incoming")) | J6: =IF($A6="","",SUMIFS(Sales!$C:$C,Sales!$B:$B,$A6)) | K6: =IF($A6="","",MAX(0,N($F6)+N($H6)-N($J6))) | L6: =IF($A6="","",$K6*N($D6)) | M6: =IF($A6="","",IF($K6<=0,"OUT OF STOCK",IF($K6<=N($G6),IF(N($I6)>0,"LOW - ON ORDER","REORDER NOW"),"OK"))) | N6: =IF($A6="","",SUMIFS(Sales!$C:$C,Sales!$B:$B,$A6,Sales!$A:$A,">="&(TODAY()-30))) | O6: =IF($A6="","",IF(N($N6)=0,"no recent sales",MAX(0,ROUND($K6/($N6/30),0))))
A7: 84879 | B7: Assorted Colour Bird Ornament | C7: Decor | D7: 0.97 | E7: 1.62 | F7: 5351 | G7: 1249 | H7: =IF($A7="","",SUMIFS('Stock In'!$C:$C,'Stock In'!$B:$B,$A7,'Stock In'!$E:$E,"Received")) | I7: =IF($A7="","",SUMIFS('Stock In'!$C:$C,'Stock In'!$B:$B,$A7,'Stock In'!$E:$E,"Incoming")) | J7: =IF($A7="","",SUMIFS(Sales!$C:$C,Sales!$B:$B,$A7)) | K7: =IF($A7="","",MAX(0,N($F7)+N($H7)-N($J7))) | L7: =IF($A7="","",$K7*N($D7)) | M7: =IF($A7="","",IF($K7<=0,"OUT OF STOCK",IF($K7<=N($G7),IF(N($I7)>0,"LOW - ON ORDER","REORDER NOW"),"OK"))) | N7: =IF($A7="","",SUMIFS(Sales!$C:$C,Sales!$B:$B,$A7,Sales!$A:$A,">="&(TODAY()-30))) | O7: =IF($A7="","",IF(N($N7)=0,"no recent sales",MAX(0,ROUND($K7/($N7/30),0))))
A8: 22720 | B8: Set Of 3 Cake Tins Pantry Design | C8: Kitchen | D8: 3.06 | E8: 5.09 | F8: 1208 | G8: 282 | H8: =IF($A8="","",SUMIFS('Stock In'!$C:$C,'Stock In'!$B:$B,$A8,'Stock In'!$E:$E,"Received")) | I8: =IF($A8="","",SUMIFS('Stock In'!$C:$C,'Stock In'!$B:$B,$A8,'Stock In'!$E:$E,"Incoming")) | J8: =IF($A8="","",SUMIFS(Sales!$C:$C,Sales!$B:$B,$A8)) | K8: =IF($A8="","",MAX(0,N($F8)+N($H8)-N($J8))) | L8: =IF($A8="","",$K8*N($D8)) | M8: =IF($A8="","",IF($K8<=0,"OUT OF STOCK",IF($K8<=N($G8),IF(N($I8)>0,"LOW - ON ORDER","REORDER NOW"),"OK"))) | N8: =IF($A8="","",SUMIFS(Sales!$C:$C,Sales!$B:$B,$A8,Sales!$A:$A,">="&(TODAY()-30))) | O8: =IF($A8="","",IF(N($N8)=0,"no recent sales",MAX(0,ROUND($K8/($N8/30),0))))
A9: 21212 | B9: Pack Of 72 Retrospot Cake Cases | C9: Kitchen | D9: 0.35 | E9: 0.58 | F9: 5970 | G9: 1393 | H9: =IF($A9="","",SUMIFS('Stock In'!$C:$C,'Stock In'!$B:$B,$A9,'Stock In'!$E:$E,"Received")) | I9: =IF($A9="","",SUMIFS('Stock In'!$C:$C,'Stock In'!$B:$B,$A9,'Stock In'!$E:$E,"Incoming")) | J9: =IF($A9="","",SUMIFS(Sales!$C:$C,Sales!$B:$B,$A9)) | K9: =IF($A9="","",MAX(0,N($F9)+N($H9)-N($J9))) | L9: =IF($A9="","",$K9*N($D9)) | M9: =IF($A9="","",IF($K9<=0,"OUT OF STOCK",IF($K9<=N($G9),IF(N($I9)>0,"LOW - ON ORDER","REORDER NOW"),"OK"))) | N9: =IF($A9="","",SUMIFS(Sales!$C:$C,Sales!$B:$B,$A9,Sales!$A:$A,">="&(TODAY()-30))) | O9: =IF($A9="","",IF(N($N9)=0,"no recent sales",MAX(0,ROUND($K9/($N9/30),0))))
A10: 22383 | B10: Lunch Bag Suki Design | C10: Bags | D10: 1.08 | E10: 1.8 | F10: 2048 | G10: 478 | H10: =IF($A10="","",SUMIFS('Stock In'!$C:$C,'Stock In'!$B:$B,$A10,'Stock In'!$E:$E,"Received")) | I10: =IF($A10="","",SUMIFS('Stock In'!$C:$C,'Stock In'!$B:$B,$A10,'Stock In'!$E:$E,"Incoming")) | J10: =IF($A10="","",SUMIFS(Sales!$C:$C,Sales!$B:$B,$A10)) | K10: =IF($A10="","",MAX(0,N($F10)+N($H10)-N($J10))) | L10: =IF($A10="","",$K10*N($D10)) | M10: =IF($A10="","",IF($K10<=0,"OUT OF STOCK",IF($K10<=N($G10),IF(N($I10)>0,"LOW - ON ORDER","REORDER NOW"),"OK"))) | N10: =IF($A10="","",SUMIFS(Sales!$C:$C,Sales!$B:$B,$A10,Sales!$A:$A,">="&(TODAY()-30))) | O10: =IF($A10="","",IF(N($N10)=0,"no recent sales",MAX(0,ROUND($K10/($N10/30),0))))
A11: 22197 | B11: Small Popcorn Holder | C11: Kitchen | D11: 0.54 | E11: 0.9 | F11: 6850 | G11: 1598 | H11: =IF($A11="","",SUMIFS('Stock In'!$C:$C,'Stock In'!$B:$B,$A11,'Stock In'!$E:$E,"Received")) | I11: =IF($A11="","",SUMIFS('Stock In'!$C:$C,'Stock In'!$B:$B,$A11,'Stock In'!$E:$E,"Incoming")) | J11: =IF($A11="","",SUMIFS(Sales!$C:$C,Sales!$B:$B,$A11)) | K11: =IF($A11="","",MAX(0,N($F11)+N($H11)-N($J11))) | L11: =IF($A11="","",$K11*N($D11)) | M11: =IF($A11="","",IF($K11<=0,"OUT OF STOCK",IF($K11<=N($G11),IF(N($I11)>0,"LOW - ON ORDER","REORDER NOW"),"OK"))) | N11: =IF($A11="","",SUMIFS(Sales!$C:$C,Sales!$B:$B,$A11,Sales!$A:$A,">="&(TODAY()-30))) | O11: =IF($A11="","",IF(N($N11)=0,"no recent sales",MAX(0,ROUND($K11/($N11/30),0))))
A12: 22386 | B12: Jumbo Bag Pink Polkadot | C12: Bags | D12: 1.19 | E12: 1.98 | F12: 3468 | G12: 809 | H12: =IF($A12="","",SUMIFS('Stock In'!$C:$C,'Stock In'!$B:$B,$A12,'Stock In'!$E:$E,"Received")) | I12: =IF($A12="","",SUMIFS('Stock In'!$C:$C,'Stock In'!$B:$B,$A12,'Stock In'!$E:$E,"Incoming")) | J12: =IF($A12="","",SUMIFS(Sales!$C:$C,Sales!$B:$B,$A12)) | K12: =IF($A12="","",MAX(0,N($F12)+N($H12)-N($J12))) | L12: =IF($A12="","",$K12*N($D12)) | M12: =IF($A12="","",IF($K12<=0,"OUT OF STOCK",IF($K12<=N($G12),IF(N($I12)>0,"LOW - ON ORDER","REORDER NOW"),"OK"))) | N12: =IF($A12="","",SUMIFS(Sales!$C:$C,Sales!$B:$B,$A12,Sales!$A:$A,">="&(TODAY()-30))) | O12: =IF($A12="","",IF(N($N12)=0,"no recent sales",MAX(0,ROUND($K12/($N12/30),0))))
A13: 20727 | B13: Lunch Bag Black Skull | C13: Bags | D13: 1.1 | E13: 1.83 | F13: 1918 | G13: 447 | H13: =IF($A13="","",SUMIFS('Stock In'!$C:$C,'Stock In'!$B:$B,$A13,'Stock In'!$E:$E,"Received")) | I13: =IF($A13="","",SUMIFS('Stock In'!$C:$C,'Stock In'!$B:$B,$A13,'Stock In'!$E:$E,"Incoming")) | J13: =IF($A13="","",SUMIFS(Sales!$C:$C,Sales!$B:$B,$A13)) | K13: =IF($A13="","",MAX(0,N($F13)+N($H13)-N($J13))) | L13: =IF($A13="","",$K13*N($D13)) | M13: =IF($A13="","",IF($K13<=0,"OUT OF STOCK",IF($K13<=N($G13),IF(N($I13)>0,"LOW - ON ORDER","REORDER NOW"),"OK"))) | N13: =IF($A13="","",SUMIFS(Sales!$C:$C,Sales!$B:$B,$A13,Sales!$A:$A,">="&(TODAY()-30))) | O13: =IF($A13="","",IF(N($N13)=0,"no recent sales",MAX(0,ROUND($K13/($N13/30),0))))
... A16: 22469 | B16: Heart Of Wicker Small | C16: Decor | D16: 1.07 | E16: 1.79 | F16: 2718 | G16: 634 | H16: =IF($A16="","",SUMIFS('Stock In'!$C:$C,'Stock In'!$B:$B,$A16,'Stock In'!$E:$E,"Received")) | I16: =IF($A16="","",SUMIFS('Stock In'!$C:$C,'Stock In'!$B:$B,$A16,'Stock In'!$E:$E,"Incoming")) | J16: =IF($A16="","",SUMIFS(Sales!$C:$C,Sales!$B:$B,$A16)) | K16: =IF($A16="","",MAX(0,N($F16)+N($H16)-N($J16))) | L16: =IF($A16="","",$K16*N($D16)) | M16: =IF($A16="","",IF($K16<=0,"OUT OF STOCK",IF($K16<=N($G16),IF(N($I16)>0,"LOW - ON ORDER","REORDER NOW"),"OK"))) | N16: =IF($A16="","",SUMIFS(Sales!$C:$C,Sales!$B:$B,$A16,Sales!$A:$A,">="&(TODAY()-30))) | O16: =IF($A16="","",IF(N($N16)=0,"no recent sales",MAX(0,ROUND($K16/($N16/30),0))))
H17: =IF($A17="","",SUMIFS('Stock In'!$C:$C,'Stock In'!$B:$B,$A17,'Stock In'!$E:$E,"Received")) | I17: =IF($A17="","",SUMIFS('Stock In'!$C:$C,'Stock In'!$B:$B,$A17,'Stock In'!$E:$E,"Incoming")) | J17: =IF($A17="","",SUMIFS(Sales!$C:$C,Sales!$B:$B,$A17)) | K17: =IF($A17="","",MAX(0,N($F17)+N($H17)-N($J17))) | L17: =IF($A17="","",$K17*N($D17)) | M17: =IF($A17="","",IF($K17<=0,"OUT OF STOCK",IF($K17<=N($G17),IF(N($I17)>0,"LOW - ON ORDER","REORDER NOW"),"OK"))) | N17: =IF($A17="","",SUMIFS(Sales!$C:$C,Sales!$B:$B,$A17,Sales!$A:$A,">="&(TODAY()-30))) | O17: =IF($A17="","",IF(N($N17)=0,"no recent sales",MAX(0,ROUND($K17/($N17/30),0))))
H18: =IF($A18="","",SUMIFS('Stock In'!$C:$C,'Stock In'!$B:$B,$A18,'Stock In'!$E:$E,"Received")) | I18: =IF($A18="","",SUMIFS('Stock In'!$C:$C,'Stock In'!$B:$B,$A18,'Stock In'!$E:$E,"Incoming")) | J18: =IF($A18="","",SUMIFS(Sales!$C:$C,Sales!$B:$B,$A18)) | K18: =IF($A18="","",MAX(0,N($F18)+N($H18)-N($J18))) | L18: =IF($A18="","",$K18*N($D18)) | M18: =IF($A18="","",IF($K18<=0,"OUT OF STOCK",IF($K18<=N($G18),IF(N($I18)>0,"LOW - ON ORDER","REORDER NOW"),"OK"))) | N18: =IF($A18="","",SUMIFS(Sales!$C:$C,Sales!$B:$B,$A18,Sales!$A:$A,">="&(TODAY()-30))) | O18: =IF($A18="","",IF(N($N18)=0,"no recent sales",MAX(0,ROUND($K18/($N18/30),0))))
H19: =IF($A19="","",SUMIFS('Stock In'!$C:$C,'Stock In'!$B:$B,$A19,'Stock In'!$E:$E,"Received")) | I19: =IF($A19="","",SUMIFS('Stock In'!$C:$C,'Stock In'!$B:$B,$A19,'Stock In'!$E:$E,"Incoming")) | J19: =IF($A19="","",SUMIFS(Sales!$C:$C,Sales!$B:$B,$A19)) | K19: =IF($A19="","",MAX(0,N($F19)+N($H19)-N($J19))) | L19: =IF($A19="","",$K19*N($D19)) | M19: =IF($A19="","",IF($K19<=0,"OUT OF STOCK",IF($K19<=N($G19),IF(N($I19)>0,"LOW - ON ORDER","REORDER NOW"),"OK"))) | N19: =IF($A19="","",SUMIFS(Sales!$C:$C,Sales!$B:$B,$A19,Sales!$A:$A,">="&(TODAY()-30))) | O19: =IF($A19="","",IF(N($N19)=0,"no recent sales",MAX(0,ROUND($K19/($N19/30),0))))
H20: =IF($A20="","",SUMIFS('Stock In'!$C:$C,'Stock In'!$B:$B,$A20,'Stock In'!$E:$E,"Received")) | I20: =IF($A20="","",SUMIFS('Stock In'!$C:$C,'Stock In'!$B:$B,$A20,'Stock In'!$E:$E,"Incoming")) | J20: =IF($A20="","",SUMIFS(Sales!$C:$C,Sales!$B:$B,$A20)) | K20: =IF($A20="","",MAX(0,N($F20)+N($H20)-N($J20))) | L20: =IF($A20="","",$K20*N($D20)) | M20: =IF($A20="","",IF($K20<=0,"OUT OF STOCK",IF($K20<=N($G20),IF(N($I20)>0,"LOW - ON ORDER","REORDER NOW"),"OK"))) | N20: =IF($A20="","",SUMIFS(Sales!$C:$C,Sales!$B:$B,$A20,Sales!$A:$A,">="&(TODAY()-30))) | O20: =IF($A20="","",IF(N($N20)=0,"no recent sales",MAX(0,ROUND($K20/($N20/30),0))))
H21: =IF($A21="","",SUMIFS('Stock In'!$C:$C,'Stock In'!$B:$B,$A21,'Stock In'!$E:$E,"Received")) | I21: =IF($A21="","",SUMIFS('Stock In'!$C:$C,'Stock In'!$B:$B,$A21,'Stock In'!$E:$E,"Incoming")) | J21: =IF($A21="","",SUMIFS(Sales!$C:$C,Sales!$B:$B,$A21)) | K21: =IF($A21="","",MAX(0,N($F21)+N($H21)-N($J21))) | L21: =IF($A21="","",$K21*N($D21)) | M21: =IF($A21="","",IF($K21<=0,"OUT OF STOCK",IF($K21<=N($G21),IF(N($I21)>0,"LOW - ON ORDER","REORDER NOW"),"OK"))) | N21: =IF($A21="","",SUMIFS(Sales!$C:$C,Sales!$B:$B,$A21,Sales!$A:$A,">="&(TODAY()-30))) | O21: =IF($A21="","",IF(N($N21)=0,"no recent sales",MAX(0,ROUND($K21/($N21/30),0))))
H22: =IF($A22="","",SUMIFS('Stock In'!$C:$C,'Stock In'!$B:$B,$A22,'Stock In'!$E:$E,"Received")) | I22: =IF($A22="","",SUMIFS('Stock In'!$C:$C,'Stock In'!$B:$B,$A22,'Stock In'!$E:$E,"Incoming")) | J22: =IF($A22="","",SUMIFS(Sales!$C:$C,Sales!$B:$B,$A22)) | K22: =IF($A22="","",MAX(0,N($F22)+N($H22)-N($J22))) | L22: =IF($A22="","",$K22*N($D22)) | M22: =IF($A22="","",IF($K22<=0,"OUT OF STOCK",IF($K22<=N($G22),IF(N($I22)>0,"LOW - ON ORDER","REORDER NOW"),"OK"))) | N22: =IF($A22="","",SUMIFS(Sales!$C:$C,Sales!$B:$B,$A22,Sales!$A:$A,">="&(TODAY()-30))) | O22: =IF($A22="","",IF(N($N22)=0,"no recent sales",MAX(0,ROUND($K22/($N22/30),0))))
H23: =IF($A23="","",SUMIFS('Stock In'!$C:$C,'Stock In'!$B:$B,$A23,'Stock In'!$E:$E,"Received")) | I23: =IF($A23="","",SUMIFS('Stock In'!$C:$C,'Stock In'!$B:$B,$A23,'Stock In'!$E:$E,"Incoming")) | J23: =IF($A23="","",SUMIFS(Sales!$C:$C,Sales!$B:$B,$A23)) | K23: =IF($A23="","",MAX(0,N($F23)+N($H23)-N($J23))) | L23: =IF($A23="","",$K23*N($D23)) | M23: =IF($A23="","",IF($K23<=0,"OUT OF STOCK",IF($K23<=N($G23),IF(N($I23)>0,"LOW - ON ORDER","REORDER NOW"),"OK"))) | N23: =IF($A23="","",SUMIFS(Sales!$C:$C,Sales!$B:$B,$A23,Sales!$A:$A,">="&(TODAY()-30))) | O23: =IF($A23="","",IF(N($N23)=0,"no recent sales",MAX(0,ROUND($K23/($N23/30),0))))
H24: =IF($A24="","",SUMIFS('Stock In'!$C:$C,'Stock In'!$B:$B,$A24,'Stock In'!$E:$E,"Received")) | I24: =IF($A24="","",SUMIFS('Stock In'!$C:$C,'Stock In'!$B:$B,$A24,'Stock In'!$E:$E,"Incoming")) | J24: =IF($A24="","",SUMIFS(Sales!$C:$C,Sales!$B:$B,$A24)) | K24: =IF($A24="","",MAX(0,N($F24)+N($H24)-N($J24))) | L24: =IF($A24="","",$K24*N($D24)) | M24: =IF($A24="","",IF($K24<=0,"OUT OF STOCK",IF($K24<=N($G24),IF(N($I24)>0,"LOW - ON ORDER","REORDER NOW"),"OK"))) | N24: =IF($A24="","",SUMIFS(Sales!$C:$C,Sales!$B:$B,$A24,Sales!$A:$A,">="&(TODAY()-30))) | O24: =IF($A24="","",IF(N($N24)=0,"no recent sales",MAX(0,ROUND($K24/($N24/30),0))))
H25: =IF($A25="","",SUMIFS('Stock In'!$C:$C,'Stock In'!$B:$B,$A25,'Stock In'!$E:$E,"Received")) | I25: =IF($A25="","",SUMIFS('Stock In'!$C:$C,'Stock In'!$B:$B,$A25,'Stock In'!$E:$E,"Incoming")) | J25: =IF($A25="","",SUMIFS(Sales!$C:$C,Sales!$B:$B,$A25)) | K25: =IF($A25="","",MAX(0,N($F25)+N($H25)-N($J25))) | L25: =IF($A25="","",$K25*N($D25)) | M25: =IF($A25="","",IF($K25<=0,"OUT OF STOCK",IF($K25<=N($G25),IF(N($I25)>0,"LOW - ON ORDER","REORDER NOW"),"OK"))) | N25: =IF($A25="","",SUMIFS(Sales!$C:$C,Sales!$B:$B,$A25,Sales!$A:$A,">="&(TODAY()-30))) | O25: =IF($A25="","",IF(N($N25)=0,"no recent sales",MAX(0,ROUND($K25/($N25/30),0))))
H26: =IF($A26="","",SUMIFS('Stock In'!$C:$C,'Stock In'!$B:$B,$A26,'Stock In'!$E:$E,"Received")) | I26: =IF($A26="","",SUMIFS('Stock In'!$C:$C,'Stock In'!$B:$B,$A26,'Stock In'!$E:$E,"Incoming")) | J26: =IF($A26="","",SUMIFS(Sales!$C:$C,Sales!$B:$B,$A26)) | K26: =IF($A26="","",MAX(0,N($F26)+N($H26)-N($J26))) | L26: =IF($A26="","",$K26*N($D26)) | M26: =IF($A26="","",IF($K26<=0,"OUT OF STOCK",IF($K26<=N($G26),IF(N($I26)>0,"LOW - ON ORDER","REORDER NOW"),"OK"))) | N26: =IF($A26="","",SUMIFS(Sales!$C:$C,Sales!$B:$B,$A26,Sales!$A:$A,">="&(TODAY()-30))) | O26: =IF($A26="","",IF(N($N26)=0,"no recent sales",MAX(0,ROUND($K26/($N26/30),0))))
H27: =IF($A27="","",SUMIFS('Stock In'!$C:$C,'Stock In'!$B:$B,$A27,'Stock In'!$E:$E,"Received")) | I27: =IF($A27="","",SUMIFS('Stock In'!$C:$C,'Stock In'!$B:$B,$A27,'Stock In'!$E:$E,"Incoming")) | J27: =IF($A27="","",SUMIFS(Sales!$C:$C,Sales!$B:$B,$A27)) | K27: =IF($A27="","",MAX(0,N($F27)+N($H27)-N($J27))) | L27: =IF($A27="","",$K27*N($D27)) | M27: =IF($A27="","",IF($K27<=0,"OUT OF STOCK",IF($K27<=N($G27),IF(N($I27)>0,"LOW - ON ORDER","REORDER NOW"),"OK"))) | N27: =IF($A27="","",SUMIFS(Sales!$C:$C,Sales!$B:$B,$A27,Sales!$A:$A,">="&(TODAY()-30))) | O27: =IF($A27="","",IF(N($N27)=0,"no recent sales",MAX(0,ROUND($K27/($N27/30),0))))
H28: =IF($A28="","",SUMIFS('Stock In'!$C:$C,'Stock In'!$B:$B,$A28,'Stock In'!$E:$E,"Received")) | I28: =IF($A28="","",SUMIFS('Stock In'!$C:$C,'Stock In'!$B:$B,$A28,'Stock In'!$E:$E,"Incoming")) | J28: =IF($A28="","",SUMIFS(Sales!$C:$C,Sales!$B:$B,$A28)) | K28: =IF($A28="","",MAX(0,N($F28)+N($H28)-N($J28))) | L28: =IF($A28="","",$K28*N($D28)) | M28: =IF($A28="","",IF($K28<=0,"OUT OF STOCK",IF($K28<=N($G28),IF(N($I28)>0,"LOW - ON ORDER","REORDER NOW"),"OK"))) | N28: =IF($A28="","",SUMIFS(Sales!$C:$C,Sales!$B:$B,$A28,Sales!$A:$A,">="&(TODAY()-30))) | O28: =IF($A28="","",IF(N($N28)=0,"no recent sales",MAX(0,ROUND($K28/($N28/30),0))))
... H201: =IF($A201="","",SUMIFS('Stock In'!$C:$C,'Stock In'!$B:$B,$A201,'Stock In'!$E:$E,"Received")) | I201: =IF($A201="","",SUMIFS('Stock In'!$C:$C,'Stock In'!$B:$B,$A201,'Stock In'!$E:$E,"Incoming")) | J201: =IF($A201="","",SUMIFS(Sales!$C:$C,Sales!$B:$B,$A201)) | K201: =IF($A201="","",MAX(0,N($F201)+N($H201)-N($J201))) | L201: =IF($A201="","",$K201*N($D201)) | M201: =IF($A201="","",IF($K201<=0,"OUT OF STOCK",IF($K201<=N($G201),IF(N($I201)>0,"LOW - ON ORDER","REORDER NOW"),"OK"))) | N201: =IF($A201="","",SUMIFS(Sales!$C:$C,Sales!$B:$B,$A201,Sales!$A:$A,">="&(TODAY()-30))) | O201: =IF($A201="","",IF(N($N201)=0,"no recent sales",MAX(0,ROUND($K201/($N201/30),0))))

Sheet Stock In
A1: Date | B1: SKU | C1: Quantity | D1: Supplier | E1: Status | F1: PO / Reference | G1: Product (auto)
G2: =IF(B2="","",IFERROR(INDEX(Products!$B:$B,MATCH(B2,Products!$A:$A,0)),"SKU not found"))
G3: =IF(B3="","",IFERROR(INDEX(Products!$B:$B,MATCH(B3,Products!$A:$A,0)),"SKU not found"))
G4: =IF(B4="","",IFERROR(INDEX(Products!$B:$B,MATCH(B4,Products!$A:$A,0)),"SKU not found"))
G5: =IF(B5="","",IFERROR(INDEX(Products!$B:$B,MATCH(B5,Products!$A:$A,0)),"SKU not found"))
G6: =IF(B6="","",IFERROR(INDEX(Products!$B:$B,MATCH(B6,Products!$A:$A,0)),"SKU not found"))
G7: =IF(B7="","",IFERROR(INDEX(Products!$B:$B,MATCH(B7,Products!$A:$A,0)),"SKU not found"))
G8: =IF(B8="","",IFERROR(INDEX(Products!$B:$B,MATCH(B8,Products!$A:$A,0)),"SKU not found"))
G9: =IF(B9="","",IFERROR(INDEX(Products!$B:$B,MATCH(B9,Products!$A:$A,0)),"SKU not found"))
G10: =IF(B10="","",IFERROR(INDEX(Products!$B:$B,MATCH(B10,Products!$A:$A,0)),"SKU not found"))
G11: =IF(B11="","",IFERROR(INDEX(Products!$B:$B,MATCH(B11,Products!$A:$A,0)),"SKU not found"))
G12: =IF(B12="","",IFERROR(INDEX(Products!$B:$B,MATCH(B12,Products!$A:$A,0)),"SKU not found"))
G13: =IF(B13="","",IFERROR(INDEX(Products!$B:$B,MATCH(B13,Products!$A:$A,0)),"SKU not found"))
... G2001: =IF(B2001="","",IFERROR(INDEX(Products!$B:$B,MATCH(B2001,Products!$A:$A,0)),"SKU not found"))

Sheet Sales
A1: Date | B1: SKU | C1: Quantity | D1: Channel | E1: Order ID | F1: Unit Price (auto) | G1: Revenue (auto) | H1: Product (auto)
A2: 40848 | B2: 20725 | C2: 6 | D2: UK | E2: 2 invoices | F2: =IF(B2="","",IFERROR(INDEX(Products!$E:$E,MATCH(B2,Products!$A:$A,0)),0)) | G2: =IF(B2="","",N(C2)*N(F2)) | H2: =IF(B2="","",IFERROR(INDEX(Products!$B:$B,MATCH(B2,Products!$A:$A,0)),"SKU not found"))
A3: 40848 | B3: 20727 | C3: 7 | D3: UK | E3: 2 invoices | F3: =IF(B3="","",IFERROR(INDEX(Products!$E:$E,MATCH(B3,Products!$A:$A,0)),0)) | G3: =IF(B3="","",N(C3)*N(F3)) | H3: =IF(B3="","",IFERROR(INDEX(Products!$B:$B,MATCH(B3,Products!$A:$A,0)),"SKU not found"))
A4: 40848 | B4: 21212 | C4: 28 | D4: UK | E4: 3 invoices | F4: =IF(B4="","",IFERROR(INDEX(Products!$E:$E,MATCH(B4,Products!$A:$A,0)),0)) | G4: =IF(B4="","",N(C4)*N(F4)) | H4: =IF(B4="","",IFERROR(INDEX(Products!$B:$B,MATCH(B4,Products!$A:$A,0)),"SKU not found"))
A5: 40848 | B5: 21931 | C5: 112 | D5: UK | E5: 3 invoices | F5: =IF(B5="","",IFERROR(INDEX(Products!$E:$E,MATCH(B5,Products!$A:$A,0)),0)) | G5: =IF(B5="","",N(C5)*N(F5)) | H5: =IF(B5="","",IFERROR(INDEX(Products!$B:$B,MATCH(B5,Products!$A:$A,0)),"SKU not found"))
A6: 40848 | B6: 22197 | C6: 48 | D6: Ireland | E6: 2 invoices | F6: =IF(B6="","",IFERROR(INDEX(Products!$E:$E,MATCH(B6,Products!$A:$A,0)),0)) | G6: =IF(B6="","",N(C6)*N(F6)) | H6: =IF(B6="","",IFERROR(INDEX(Products!$B:$B,MATCH(B6,Products!$A:$A,0)),"SKU not found"))
A7: 40848 | B7: 22197 | C7: 238 | D7: UK | E7: 6 invoices | F7: =IF(B7="","",IFERROR(INDEX(Products!$E:$E,MATCH(B7,Products!$A:$A,0)),0)) | G7: =IF(B7="","",N(C7)*N(F7)) | H7: =IF(B7="","",IFERROR(INDEX(Products!$B:$B,MATCH(B7,Products!$A:$A,0)),"SKU not found"))
A8: 40848 | B8: 22383 | C8: 6 | D8: UK | E8: 2 invoices | F8: =IF(B8="","",IFERROR(INDEX(Products!$E:$E,MATCH(B8,Products!$A:$A,0)),0)) | G8: =IF(B8="","",N(C8)*N(F8)) | H8: =IF(B8="","",IFERROR(INDEX(Products!$B:$B,MATCH(B8,Products!$A:$A,0)),"SKU not found"))
A9: 40848 | B9: 22386 | C9: 43 | D9: UK | E9: 3 invoices | F9: =IF(B9="","",IFERROR(INDEX(Products!$E:$E,MATCH(B9,Products!$A:$A,0)),0)) | G9: =IF(B9="","",N(C9)*N(F9)) | H9: =IF(B9="","",IFERROR(INDEX(Products!$B:$B,MATCH(B9,Products!$A:$A,0)),"SKU not found"))
A10: 40848 | B10: 22423 | C10: 10 | D10: Ireland | E10: 2 invoices | F10: =IF(B10="","",IFERROR(INDEX(Products!$E:$E,MATCH(B10,Products!$A:$A,0)),0)) | G10: =IF(B10="","",N(C10)*N(F10)) | H10: =IF(B10="","",IFERROR(INDEX(Products!$B:$B,MATCH(B10,Products!$A:$A,0)),"SKU not found"))
A11: 40848 | B11: 22423 | C11: 11 | D11: UK | E11: 7 invoices | F11: =IF(B11="","",IFERROR(INDEX(Products!$E:$E,MATCH(B11,Products!$A:$A,0)),0)) | G11: =IF(B11="","",N(C11)*N(F11)) | H11: =IF(B11="","",IFERROR(INDEX(Products!$B:$B,MATCH(B11,Products!$A:$A,0)),"SKU not found"))
A12: 40848 | B12: 22457 | C12: 12 | D12: UK | E12: 2 invoices | F12: =IF(B12="","",IFERROR(INDEX(Products!$E:$E,MATCH(B12,Products!$A:$A,0)),0)) | G12: =IF(B12="","",N(C12)*N(F12)) | H12: =IF(B12="","",IFERROR(INDEX(Products!$B:$B,MATCH(B12,Products!$A:$A,0)),"SKU not found"))
A13: 40848 | B13: 22469 | C13: 12 | D13: Ireland | E13: 1 invoices | F13: =IF(B13="","",IFERROR(INDEX(Products!$E:$E,MATCH(B13,Products!$A:$A,0)),0)) | G13: =IF(B13="","",N(C13)*N(F13)) | H13: =IF(B13="","",IFERROR(INDEX(Products!$B:$B,MATCH(B13,Products!$A:$A,0)),"SKU not found"))
... A705: 40886 | B705: 85123A | C705: 4 | D705: UK | E705: 2 invoices | F705: =IF(B705="","",IFERROR(INDEX(Products!$E:$E,MATCH(B705,Products!$A:$A,0)),0)) | G705: =IF(B705="","",N(C705)*N(F705)) | H705: =IF(B705="","",IFERROR(INDEX(Products!$B:$B,MATCH(B705,Products!$A:$A,0)),"SKU not found"))
F706: =IF(B706="","",IFERROR(INDEX(Products!$E:$E,MATCH(B706,Products!$A:$A,0)),0)) | G706: =IF(B706="","",N(C706)*N(F706)) | H706: =IF(B706="","",IFERROR(INDEX(Products!$B:$B,MATCH(B706,Products!$A:$A,0)),"SKU not found"))
F707: =IF(B707="","",IFERROR(INDEX(Products!$E:$E,MATCH(B707,Products!$A:$A,0)),0)) | G707: =IF(B707="","",N(C707)*N(F707)) | H707: =IF(B707="","",IFERROR(INDEX(Products!$B:$B,MATCH(B707,Products!$A:$A,0)),"SKU not found"))
F708: =IF(B708="","",IFERROR(INDEX(Products!$E:$E,MATCH(B708,Products!$A:$A,0)),0)) | G708: =IF(B708="","",N(C708)*N(F708)) | H708: =IF(B708="","",IFERROR(INDEX(Products!$B:$B,MATCH(B708,Products!$A:$A,0)),"SKU not found"))
F709: =IF(B709="","",IFERROR(INDEX(Products!$E:$E,MATCH(B709,Products!$A:$A,0)),0)) | G709: =IF(B709="","",N(C709)*N(F709)) | H709: =IF(B709="","",IFERROR(INDEX(Products!$B:$B,MATCH(B709,Products!$A:$A,0)),"SKU not found"))
F710: =IF(B710="","",IFERROR(INDEX(Products!$E:$E,MATCH(B710,Products!$A:$A,0)),0)) | G710: =IF(B710="","",N(C710)*N(F710)) | H710: =IF(B710="","",IFERROR(INDEX(Products!$B:$B,MATCH(B710,Products!$A:$A,0)),"SKU not found"))
F711: =IF(B711="","",IFERROR(INDEX(Products!$E:$E,MATCH(B711,Products!$A:$A,0)),0)) | G711: =IF(B711="","",N(C711)*N(F711)) | H711: =IF(B711="","",IFERROR(INDEX(Products!$B:$B,MATCH(B711,Products!$A:$A,0)),"SKU not found"))
F712: =IF(B712="","",IFERROR(INDEX(Products!$E:$E,MATCH(B712,Products!$A:$A,0)),0)) | G712: =IF(B712="","",N(C712)*N(F712)) | H712: =IF(B712="","",IFERROR(INDEX(Products!$B:$B,MATCH(B712,Products!$A:$A,0)),"SKU not found"))
F713: =IF(B713="","",IFERROR(INDEX(Products!$E:$E,MATCH(B713,Products!$A:$A,0)),0)) | G713: =IF(B713="","",N(C713)*N(F713)) | H713: =IF(B713="","",IFERROR(INDEX(Products!$B:$B,MATCH(B713,Products!$A:$A,0)),"SKU not found"))
F714: =IF(B714="","",IFERROR(INDEX(Products!$E:$E,MATCH(B714,Products!$A:$A,0)),0)) | G714: =IF(B714="","",N(C714)*N(F714)) | H714: =IF(B714="","",IFERROR(INDEX(Products!$B:$B,MATCH(B714,Products!$A:$A,0)),"SKU not found"))
F715: =IF(B715="","",IFERROR(INDEX(Products!$E:$E,MATCH(B715,Products!$A:$A,0)),0)) | G715: =IF(B715="","",N(C715)*N(F715)) | H715: =IF(B715="","",IFERROR(INDEX(Products!$B:$B,MATCH(B715,Products!$A:$A,0)),"SKU not found"))
F716: =IF(B716="","",IFERROR(INDEX(Products!$E:$E,MATCH(B716,Products!$A:$A,0)),0)) | G716: =IF(B716="","",N(C716)*N(F716)) | H716: =IF(B716="","",IFERROR(INDEX(Products!$B:$B,MATCH(B716,Products!$A:$A,0)),"SKU not found"))
F717: =IF(B717="","",IFERROR(INDEX(Products!$E:$E,MATCH(B717,Products!$A:$A,0)),0)) | G717: =IF(B717="","",N(C717)*N(F717)) | H717: =IF(B717="","",IFERROR(INDEX(Products!$B:$B,MATCH(B717,Products!$A:$A,0)),"SKU not found"))
... F2001: =IF(B2001="","",IFERROR(INDEX(Products!$E:$E,MATCH(B2001,Products!$A:$A,0)),0)) | G2001: =IF(B2001="","",N(C2001)*N(F2001)) | H2001: =IF(B2001="","",IFERROR(INDEX(Products!$B:$B,MATCH(B2001,Products!$A:$A,0)),"SKU not found"))

Sheet Dashboard
A1: Inventory Dashboard
A2: ="Updated: "&TEXT(TODAY(),"dd-mmm-yyyy")
D3: Stock by SKU
A4: Active SKUs | B4: =COUNTIF(Products!$A$2:$A$201,"?*") | D4: SKU | E4: Product | F4: Current Stock | G4: Reorder Level | H4: Status
A5: Total units in stock | B5: =SUM(Products!$K$2:$K$201) | D5: =IF(Products!A2="","",Products!A2) | E5: =IF(Products!A2="","",Products!B2) | F5: =IF(Products!A2="","",Products!K2) | G5: =IF(Products!A2="","",Products!G2) | H5: =IF(Products!A2="","",Products!M2)
A6: Stock value (at cost) | B6: =SUM(Products!$L$2:$L$201) | D6: =IF(Products!A3="","",Products!A3) | E6: =IF(Products!A3="","",Products!B3) | F6: =IF(Products!A3="","",Products!K3) | G6: =IF(Products!A3="","",Products!G3) | H6: =IF(Products!A3="","",Products!M3)
A7: Units on order (incoming) | B7: =SUM(Products!$I$2:$I$201) | D7: =IF(Products!A4="","",Products!A4) | E7: =IF(Products!A4="","",Products!B4) | F7: =IF(Products!A4="","",Products!K4) | G7: =IF(Products!A4="","",Products!G4) | H7: =IF(Products!A4="","",Products!M4)
A8: SKUs to reorder now | B8: =COUNTIF(Products!$M$2:$M$201,"REORDER NOW") | D8: =IF(Products!A5="","",Products!A5) | E8: =IF(Products!A5="","",Products!B5) | F8: =IF(Products!A5="","",Products!K5) | G8: =IF(Products!A5="","",Products!G5) | H8: =IF(Products!A5="","",Products!M5)
A9: SKUs low but on order | B9: =COUNTIF(Products!$M$2:$M$201,"LOW - ON ORDER") | D9: =IF(Products!A6="","",Products!A6) | E9: =IF(Products!A6="","",Products!B6) | F9: =IF(Products!A6="","",Products!K6) | G9: =IF(Products!A6="","",Products!G6) | H9: =IF(Products!A6="","",Products!M6)
A10: SKUs out of stock | B10: =COUNTIF(Products!$M$2:$M$201,"OUT OF STOCK") | D10: =IF(Products!A7="","",Products!A7) | E10: =IF(Products!A7="","",Products!B7) | F10: =IF(Products!A7="","",Products!K7) | G10: =IF(Products!A7="","",Products!G7) | H10: =IF(Products!A7="","",Products!M7)
A11: Units sold (all time) | B11: =SUM(Sales!$C$2:$C$2001) | D11: =IF(Products!A8="","",Products!A8) | E11: =IF(Products!A8="","",Products!B8) | F11: =IF(Products!A8="","",Products!K8) | G11: =IF(Products!A8="","",Products!G8) | H11: =IF(Products!A8="","",Products!M8)
A12: Revenue (all time) | B12: =SUM(Sales!$G$2:$G$2001) | D12: =IF(Products!A9="","",Products!A9) | E12: =IF(Products!A9="","",Products!B9) | F12: =IF(Products!A9="","",Products!K9) | G12: =IF(Products!A9="","",Products!G9) | H12: =IF(Products!A9="","",Products!M9)
A13: Revenue (last 30 days) | B13: =SUMIFS(Sales!$G$2:$G$2001,Sales!$A$2:$A$2001,">="&(TODAY()-30)) | D13: =IF(Products!A10="","",Products!A10) | E13: =IF(Products!A10="","",Products!B10) | F13: =IF(Products!A10="","",Products!K10) | G13: =IF(Products!A10="","",Products!G10) | H13: =IF(Products!A10="","",Products!M10)
D14: =IF(Products!A11="","",Products!A11) | E14: =IF(Products!A11="","",Products!B11) | F14: =IF(Products!A11="","",Products!K11) | G14: =IF(Products!A11="","",Products!G11) | H14: =IF(Products!A11="","",Products!M11)
D15: =IF(Products!A12="","",Products!A12) | E15: =IF(Products!A12="","",Products!B12) | F15: =IF(Products!A12="","",Products!K12) | G15: =IF(Products!A12="","",Products!G12) | H15: =IF(Products!A12="","",Products!M12)
A16: Sales by market (country) | D16: =IF(Products!A13="","",Products!A13) | E16: =IF(Products!A13="","",Products!B13) | F16: =IF(Products!A13="","",Products!K13) | G16: =IF(Products!A13="","",Products!G13) | H16: =IF(Products!A13="","",Products!M13)
A17: Market | B17: Revenue | D17: =IF(Products!A14="","",Products!A14) | E17: =IF(Products!A14="","",Products!B14) | F17: =IF(Products!A14="","",Products!K14) | G17: =IF(Products!A14="","",Products!G14) | H17: =IF(Products!A14="","",Products!M14)
A18: UK | B18: =SUMIFS(Sales!$G$2:$G$2001,Sales!$D$2:$D$2001,A18) | D18: =IF(Products!A15="","",Products!A15) | E18: =IF(Products!A15="","",Products!B15) | F18: =IF(Products!A15="","",Products!K15) | G18: =IF(Products!A15="","",Products!G15) | H18: =IF(Products!A15="","",Products!M15)
A19: Ireland | B19: =SUMIFS(Sales!$G$2:$G$2001,Sales!$D$2:$D$2001,A19) | D19: =IF(Products!A16="","",Products!A16) | E19: =IF(Products!A16="","",Products!B16) | F19: =IF(Products!A16="","",Products!K16) | G19: =IF(Products!A16="","",Products!G16) | H19: =IF(Products!A16="","",Products!M16)
A20: France | B20: =SUMIFS(Sales!$G$2:$G$2001,Sales!$D$2:$D$2001,A20) | D20: =IF(Products!A17="","",Products!A17) | E20: =IF(Products!A17="","",Products!B17) | F20: =IF(Products!A17="","",Products!K17) | G20: =IF(Products!A17="","",Products!G17) | H20: =IF(Products!A17="","",Products!M17)
A21: Germany | B21: =SUMIFS(Sales!$G$2:$G$2001,Sales!$D$2:$D$2001,A21) | D21: =IF(Products!A18="","",Products!A18) | E21: =IF(Products!A18="","",Products!B18) | F21: =IF(Products!A18="","",Products!K18) | G21: =IF(Products!A18="","",Products!G18) | H21: =IF(Products!A18="","",Products!M18)
A22: Other EU/Intl | B22: =SUMIFS(Sales!$G$2:$G$2001,Sales!$D$2:$D$2001,A22) | D22: =IF(Products!A19="","",Products!A19) | E22: =IF(Products!A19="","",Products!B19) | F22: =IF(Products!A19="","",Products!K19) | G22: =IF(Products!A19="","",Products!G19) | H22: =IF(Products!A19="","",Products!M19)
D23: =IF(Products!A20="","",Products!A20) | E23: =IF(Products!A20="","",Products!B20) | F23: =IF(Products!A20="","",Products!K20) | G23: =IF(Products!A20="","",Products!G20) | H23: =IF(Products!A20="","",Products!M20)
D24: =IF(Products!A21="","",Products!A21) | E24: =IF(Products!A21="","",Products!B21) | F24: =IF(Products!A21="","",Products!K21) | G24: =IF(Products!A21="","",Products!G21) | H24: =IF(Products!A21="","",Products!M21)
D25: =IF(Products!A22="","",Products!A22) | E25: =IF(Products!A22="","",Products!B22) | F25: =IF(Products!A22="","",Products!K22) | G25: =IF(Products!A22="","",Products!G22) | H25: =IF(Products!A22="","",Products!M22)
D26: =IF(Products!A23="","",Products!A23) | E26: =IF(Products!A23="","",Products!B23) | F26: =IF(Products!A23="","",Products!K23) | G26: =IF(Products!A23="","",Products!G23) | H26: =IF(Products!A23="","",Products!M23)
D27: =IF(Products!A24="","",Products!A24) | E27: =IF(Products!A24="","",Products!B24) | F27: =IF(Products!A24="","",Products!K24) | G27: =IF(Products!A24="","",Products!G24) | H27: =IF(Products!A24="","",Products!M24)
D28: =IF(Products!A25="","",Products!A25) | E28: =IF(Products!A25="","",Products!B25) | F28: =IF(Products!A25="","",Products!K25) | G28: =IF(Products!A25="","",Products!G25) | H28: =IF(Products!A25="","",Products!M25)
D29: =IF(Products!A26="","",Products!A26) | E29: =IF(Products!A26="","",Products!B26) | F29: =IF(Products!A26="","",Products!K26) | G29: =IF(Products!A26="","",Products!G26) | H29: =IF(Products!A26="","",Products!M26)
D30: =IF(Products!A27="","",Products!A27) | E30: =IF(Products!A27="","",Products!B27) | F30: =IF(Products!A27="","",Products!K27) | G30: =IF(Products!A27="","",Products!G27) | H30: =IF(Products!A27="","",Products!M27)
D31: =IF(Products!A28="","",Products!A28) | E31: =IF(Products!A28="","",Products!B28) | F31: =IF(Products!A28="","",Products!K28) | G31: =IF(Products!A28="","",Products!G28) | H31: =IF(Products!A28="","",Products!M28)
D32: =IF(Products!A29="","",Products!A29) | E32: =IF(Products!A29="","",Products!B29) | F32: =IF(Products!A29="","",Products!K29) | G32: =IF(Products!A29="","",Products!G29) | H32: =IF(Products!A29="","",Products!M29)
D33: =IF(Products!A30="","",Products!A30) | E33: =IF(Products!A30="","",Products!B30) | F33: =IF(Products!A30="","",Products!K30) | G33: =IF(Products!A30="","",Products!G30) | H33: =IF(Products!A30="","",Products!M30)
D34: =IF(Products!A31="","",Products!A31) | E34: =IF(Products!A31="","",Products!B31) | F34: =IF(Products!A31="","",Products!K31) | G34: =IF(Products!A31="","",Products!G31) | H34: =IF(Products!A31="","",Products!M31)
